binance_load/Load.py
binance_load/__init__.py
binance_load-1.0.3.dist-info/LICENSE
binance_load-1.0.3.dist-info/METADATA
binance_load-1.0.3.dist-info/WHEEL
binance_load-1.0.3.dist-info/top_level.txt
binance_load-1.0.3.dist-info/RECORD
