Metadata-Version: 2.1
Name: binance-load
Version: 1.0.3
Summary: simple module for continuous loading of temporary historical data
Author-email: Igor Rogachevich <shmeller86@gmail.com>
License: MIT License        
Project-URL: Homepage, https://github.com/shmeller86/shmeller86
Classifier: Programming Language :: Python :: 3
Classifier: License :: OSI Approved :: MIT License
Classifier: Operating System :: OS Independent
Requires-Python: >=3.7
License-File: LICENSE
